[
    {
        "id": "rex_rugs_restoration",
        "title": "Reza",
        "post": "5",
        "followers": "566"
    },
    {
        "id": "glarahome",
        "title": "Glara Home",
        "post": "1,121",
        "followers": "6,267"
    },
    {
        "id": "pacificgallery",
        "title": "Pacific Rug Gallery",
        "post": "715",
        "followers": "7,707"
    },
    {
        "id": "tabrizirugs",
        "title": "Tabrizi Rugs",
        "followers": "3,839"
    },
    {
        "id": "risarug",
        "title": "Risa Rug",
        "followers": "671"
    },
    {
        "id": "kasrazrugs",
        "title": "Kasraz Rugs",
        "followers": "460"
    },
    {
        "id": "colincampbellcarpets",
        "title": "Colin Campbell",
        "followers": "2,617"
    },
    {
        "id": "mercatohome",
        "title": "Mercato Home",
        "followers": "137"
    },
    {
        "id": "ggtgroup.ca",
        "title": "Tara Tajdari",
        "followers": "169"
    },
    {
        "id": "pazyrykrug",
        "title": "Pazyryk",
        "followers": "115"
    },
    {
        "id": "shirazrug",
        "title": "Shiraz Rug",
        "followers": "66"
    },
    {
        "id": "westcoastrugs",
        "title": "West Coast Rugs",
        "followers": "414"
    },
    {
        "id": "araratcarpet",
        "title": "ARARAT ORIENTAL RUG GALLERY",
        "followers": "112"
    },
    {
        "id": "goldenrug",
        "title": "Golden Rug",
        "followers": "112"
    },
    {
        "id": "karma.home_ca",
        "title": "Karma Home",
        "followers": "640"
    }
]
